[
{"fID":"t001","fSecondID":"s001","fClassName":"自拍神器","fClassImg":"./class/img/pic5.png"},
{"fID":"t002","fSecondID":"s001","fClassName":"百搭女鞋","fClassImg":"./class/img/pic4.png"},
{"fID":"t003","fSecondID":"s001","fClassName":"首发爆款","fClassImg":"./class/img/pic7.png"},
{"fID":"t004","fSecondID":"s001","fClassName":"休闲牛仔","fClassImg":"./class/img/pic3.png"},
{"fID":"t005","fSecondID":"s001","fClassName":"时尚潮牌","fClassImg":"./class/img/pic13.png"},
{"fID":"t006","fSecondID":"s001","fClassName":"周黑鸭","fClassImg":"./class/img/pic14.png"},
{"fID":"t007","fSecondID":"s001","fClassName":"流行阔腿裤","fClassImg":"./class/img/pic8.png"},
{"fID":"t008","fSecondID":"s002","fClassName":"POLO衫","fClassImg":"./class/img/pic1.png"},
{"fID":"t009","fSecondID":"s002","fClassName":"男士精品","fClassImg":"./class/img/pic10.png"},
{"fID":"t010","fSecondID":"s002","fClassName":"破洞牛仔","fClassImg":"./class/img/pic3.png"},
{"fID":"t011","fSecondID":"s002","fClassName":"手提包","fClassImg":"./class/img/pic12.png"},
{"fID":"t012","fSecondID":"s003","fClassName":"明星同款","fClassImg":"./class/img/pic13.png"},
{"fID":"t013","fSecondID":"s003","fClassName":"个性包臀裙","fClassImg":"./class/img/pic2.png"},
{"fID":"t014","fSecondID":"s003","fClassName":"新品连衣裙","fClassImg":"./class/img/pic8.png"},
{"fID":"t015","fSecondID":"s003","fClassName":"百搭女鞋","fClassImg":"./class/img/pic4.png"},
{"fID":"t016","fSecondID":"s004","fClassName":"七分裤裙","fClassImg":"./class/img/pic8.png"},
{"fID":"t017","fSecondID":"s004","fClassName":"潮流女装","fClassImg":"./class/img/pic2.png"},
{"fID":"t018","fSecondID":"s005","fClassName":"人鱼装","fClassImg":"./class/img/pic13.png"},
{"fID":"t019","fSecondID":"s006","fClassName":"爆款百搭","fClassImg":"./class/img/pic4.png"},
{"fID":"t020","fSecondID":"s007","fClassName":"红豆男士","fClassImg":"./class/img/pic1.png"},
{"fID":"t021","fSecondID":"s008","fClassName":"潮牌牛仔","fClassImg":"./class/img/pic3.png"},
{"fID":"t022","fSecondID":"s009","fClassName":"职场必配","fClassImg":"./class/img/pic12.png"},
{"fID":"t023","fSecondID":"s010","fClassName":"单反相机","fClassImg":"./class/img/pic11.png"},
{"fID":"t024","fSecondID":"s010","fClassName":"数码相机","fClassImg":"./class/img/pic5.png"},
{"fID":"t025","fSecondID":"s011","fClassName":"魅蓝note3","fClassImg":"./class/img/pic7.png"},
{"fID":"t026","fSecondID":"s011","fClassName":"苹果SE","fClassImg":"./class/img/pic9.png"},
{"fID":"t027","fSecondID":"s012","fClassName":"手表","fClassImg":"./class/img/pic10.png"},
{"fID":"t028","fSecondID":"s013","fClassName":"大樱桃","fClassImg":"./class/img/pic6.png"},
{"fID":"t029","fSecondID":"s014","fClassName":"周黑鸭","fClassImg":"./class/img/pic14.png"}
]